tdexpta/__init__.py
tdexpta/run.py
tdexpta/analysis/__init__.py
tdexpta/analysis/analysis.py
tdexpta/analysis/driver.py
tdexpta/analysis/search.py
tdexpta/data/__init__.py
tdexpta/data/categorize_data.py
tdexpta/data/driver.py
tdexpta/data/store_data.py
tdexpta-0.0.1.dist-info/LICENSE
tdexpta-0.0.1.dist-info/METADATA
tdexpta-0.0.1.dist-info/WHEEL
tdexpta-0.0.1.dist-info/top_level.txt
tdexpta-0.0.1.dist-info/RECORD
